{
  "enabled": true,
  "path": "/cam2",
  "url": "rtsp://admin007:admin007@192.168.1.188:554/stream1",
  "transport": "tcp",
  "reconnect_interval": 5,
  "chunk_read_size": null,
  "token": null,
  "ffmpeg": {
    "command": null,
    "use_wallclock_as_timestamps": null,
    "output_format": null,
    "video_codec": null,
    "video_bitrate": null,
    "quality": null,
    "output_framerate": null,
    "scale": "1280:-1",
    "movflags": null,
    "rtbufsize": null,
    "fflags": null,
    "flags": null,
    "avioflags": null,
    "fps_mode": null,
    "flush_packets": null,
    "extra_input_args": null,
    "extra_output_args": null,
    "log_stderr": null
  },
  "mqtt": {
    "publish_interval": 0,
    "topic_name": "surveillance/cameras/cam2/image"
  },
  "max_recording_age": "1d"
}